.gitignore
CHANGES.rst
LICENSE.txt
README.rst
distribute_setup.py
fabfile.py
setup.py
doc/Makefile
doc/conf.py
doc/index.rst
doc/make.bat
doc/pyabm.rst
doc/setup.rst
pyabm/__init__.py
pyabm/agents.py
pyabm/file_io.py
pyabm/file_io_ogr.py
pyabm/pyabmrc.linux
pyabm/pyabmrc.windows
pyabm/rcparams.default
pyabm/rcsetup.py
pyabm/statistics.py
pyabm/utility.py
pyabm.egg-info/PKG-INFO
pyabm.egg-info/SOURCES.txt
pyabm.egg-info/dependency_links.txt
pyabm.egg-info/requires.txt
pyabm.egg-info/top_level.txt
pyabm.egg-info/zip-safe