Metadata-Version: 1.1
Name: pyabm
Version: 0.3.3
Summary: Agent-based modeling toolkit
Home-page: http://rohan.sdsu.edu/~zvoleff/research/pyabm
Author: Alex Zvoleff
Author-email: azvoleff@mail.sdsu.edu
License: GPL v3 or later
Keywords: agent-based modeling ABM simulation model
Platform: UNKNOWN
Classifier: Development Status :: 3 - Alpha
Classifier: Natural Language :: English
Classifier: Topic :: Software Development
Classifier: Topic :: Scientific/Engineering
Classifier: Topic :: Scientific/Engineering :: Artificial Life
Classifier: Intended Audience :: Science/Research
Classifier: License :: OSI Approved :: GNU General Public License v3 or later (GPLv3+)
Classifier: Operating System :: OS Independent
Classifier: Programming Language :: Python
Classifier: Programming Language :: Python :: 2.7
Classifier: Topic :: Software Development :: Libraries :: Python Modules
